reset_password/__init__.py
reset_password/admin.py
reset_password/apps.py
reset_password/exceptions.py
reset_password/managers.py
reset_password/models.py
reset_password/serializers.py
reset_password/signals.py
reset_password/views.py
reset_password/migrations/0001_initial.py
reset_password/migrations/__init__.py
reset_password/templates/reset_password_email.html
drf_reset_password-1.2.9.dist-info/LICENSE
drf_reset_password-1.2.9.dist-info/METADATA
drf_reset_password-1.2.9.dist-info/WHEEL
drf_reset_password-1.2.9.dist-info/top_level.txt
drf_reset_password-1.2.9.dist-info/RECORD
